odoo/addons/product_variant_tree_qty_available/README.rst
odoo/addons/product_variant_tree_qty_available/__init__.py
odoo/addons/product_variant_tree_qty_available/__manifest__.py
odoo/addons/product_variant_tree_qty_available/i18n/es.po
odoo/addons/product_variant_tree_qty_available/i18n/it.po
odoo/addons/product_variant_tree_qty_available/i18n/product_variant_tree_qty_available.pot
odoo/addons/product_variant_tree_qty_available/models/__init__.py
odoo/addons/product_variant_tree_qty_available/models/product_product.py
odoo/addons/product_variant_tree_qty_available/models/stock_quant.py
odoo/addons/product_variant_tree_qty_available/readme/CONTRIBUTORS.md
odoo/addons/product_variant_tree_qty_available/readme/DESCRIPTION.md
odoo/addons/product_variant_tree_qty_available/readme/USAGE.md
odoo/addons/product_variant_tree_qty_available/readme/newsfragments/.gitkeep
odoo/addons/product_variant_tree_qty_available/static/description/icon.png
odoo/addons/product_variant_tree_qty_available/static/description/index.html
odoo/addons/product_variant_tree_qty_available/tests/__init__.py
odoo/addons/product_variant_tree_qty_available/tests/test_product_variant_tree_qty_available.py
odoo/addons/product_variant_tree_qty_available/views/product_views.xml
odoo14_addon_product_variant_tree_qty_available-14.0.1.0.1.dev5.dist-info/METADATA
odoo14_addon_product_variant_tree_qty_available-14.0.1.0.1.dev5.dist-info/WHEEL
odoo14_addon_product_variant_tree_qty_available-14.0.1.0.1.dev5.dist-info/top_level.txt
odoo14_addon_product_variant_tree_qty_available-14.0.1.0.1.dev5.dist-info/RECORD
